[{"number": 527, "title": "build(deps): bump third-party/youtube-dl from `c509896` to `956b8c5`", "author": "dependabot[bot]", "labels": ["dependencies", "submodules"], "assignees": [], "created_at": "2025-11-26T10:06:02+00:00", "updated_at": "2026-02-15T07:31:43+00:00", "draft": false, "milestone": null}, {"number": 525, "title": "New Crowdin updates", "author": "LizardByte-bot", "labels": ["crowdin", "l10n"], "assignees": [], "created_at": "2025-11-17T08:14:12+00:00", "updated_at": "2025-12-20T02:43:45+00:00", "draft": false, "milestone": null}, {"number": 497, "title": "refactor!: move project to standalone version", "author": "ReenigneArcher", "labels": [], "assignees": [], "created_at": "2024-08-09T19:43:31+00:00", "updated_at": "2026-02-14T20:57:10+00:00", "draft": true, "milestone": "standalone"}, {"number": 229, "title": "feat: add Plex authentification", "author": "zdimension", "labels": [], "assignees": ["ReenigneArcher"], "created_at": "2023-11-21T01:59:07+00:00", "updated_at": "2026-04-06T23:51:10+00:00", "draft": false, "milestone": null}]